soniscope_jupyter/__init__.py
soniscope_jupyter/_frontend.py
soniscope_jupyter/_version.py
soniscope_jupyter/lens_widget.py
soniscope_jupyter/rectbin_widget.py
soniscope_jupyter/nbextension/extension.js
soniscope_jupyter/tests/__init__.py
soniscope_jupyter/tests/conftest.py
soniscope_jupyter/tests/debug.py
soniscope_jupyter/tests/test_example.py
soniscope_jupyter/tests/test_nbextension_path.py
soniscope_jupyter-0.1.8.data/data/share/jupyter/labextensions/soniscope-jupyter/package.json
soniscope_jupyter-0.1.8.data/data/share/jupyter/labextensions/soniscope-jupyter/static/367.7d25d68481d43b84c244.js
soniscope_jupyter-0.1.8.data/data/share/jupyter/labextensions/soniscope-jupyter/static/480.d6f27768af1c36e951d7.js
soniscope_jupyter-0.1.8.data/data/share/jupyter/labextensions/soniscope-jupyter/static/481.9090d07b9dad4193de33.js
soniscope_jupyter-0.1.8.data/data/share/jupyter/labextensions/soniscope-jupyter/static/568.ae0ea9c2dcb2d85484ef.js
soniscope_jupyter-0.1.8.data/data/share/jupyter/labextensions/soniscope-jupyter/static/remoteEntry.c71f539f4502e38ca389.js
soniscope_jupyter-0.1.8.data/data/share/jupyter/labextensions/soniscope-jupyter/static/style.js
soniscope_jupyter-0.1.8.data/data/share/jupyter/labextensions/soniscope-jupyter/static/third-party-licenses.json
soniscope_jupyter-0.1.8.data/data/share/jupyter/nbextensions/soniscope_jupyter/extension.js
soniscope_jupyter-0.1.8.data/data/share/jupyter/nbextensions/soniscope_jupyter/index.js
soniscope_jupyter-0.1.8.data/data/share/jupyter/nbextensions/soniscope_jupyter/index.js.map
soniscope_jupyter-0.1.8.data/data/etc/jupyter/nbconfig/notebook.d/soniscope_jupyter.json
soniscope_jupyter-0.1.8.data/data/share/jupyter/labextensions/soniscope-jupyter/install.json
soniscope_jupyter-0.1.8.dist-info/METADATA
soniscope_jupyter-0.1.8.dist-info/WHEEL
soniscope_jupyter-0.1.8.dist-info/licenses/LICENSE.txt
soniscope_jupyter-0.1.8.dist-info/RECORD
